UART/UARTsend.v
module UARTsend(
	clk16x,
	rst_n,
	TransEn,
	DataToTrans,
	BufFull,
	tx);

	//---Ports declearation: generated by Robei---
	input clk16x;
	input rst_n;
	input TransEn;
	input [7:0] DataToTrans;
	output BufFull;
	output tx;

	wire clk16x;
	wire rst_n;
	wire TransEn;
	wire [7:0] DataToTrans;
	reg BufFull;
	reg tx;

	//----Code starts here: integrated by Robei-----
	
	/*    capture the rising edge of TransEn    */
	reg [7:0] cnt; 
	reg TransEn_r;
	wire pos_tri;
	always@(posedge clk16x or negedge rst_n)
	begin
	    if(!rst_n)
	        TransEn_r <= 1'b0;
	    else
	        TransEn_r <= TransEn;
	end
	assign pos_tri = ~TransEn_r & TransEn;
	
	/*
	*    when the rising edge of DataEn comes up, load the Data to buffer
	*/
	reg [7:0] ShiftReg;
	always@(posedge pos_tri or negedge rst_n)
	begin
	    if(!rst_n)
	        ShiftReg <= 8'b0;
	    else
	        ShiftReg <= DataToTrans;
	end
	//----------------------------------------------    
	/*     counter control      */
	reg cnt_en;
	always@(posedge clk16x or negedge rst_n)
	begin
	    if(!rst_n)
	        begin
	            cnt_en  <= 1'b0;
	            BufFull <= 1'b0;
	        end
	    else if(pos_tri==1'b1)
	        begin
	            cnt_en  <=1'b1;
	            BufFull <=1'b1;
	        end
	    else if(cnt==8'd160)
	        begin
	            cnt_en<=1'b0;
	            BufFull <=1'b0;
	        end
	end
	
	//---------------------------------------------
	/*      counter module        */
	
	always@(posedge clk16x or negedge rst_n)
	begin
	    if(!rst_n)
	        cnt<=8'd0;
	    else if(cnt_en)
	        cnt<=cnt+1;
	    else
	        cnt<=8'd0;
	end
	
	//---------------------------------------------
	/*      transmit module        */
	
	always@(posedge clk16x or negedge rst_n)
	begin
	    if(!rst_n)
	        begin
	            tx <= 1'b1;
	        end
	    else if(cnt_en)
	        case(cnt)
	            8'd0   :  tx <= 1'b0;
	            8'd16  :  tx <= ShiftReg[0];
	            8'd32  :  tx <= ShiftReg[1];
	            8'd48  :  tx <= ShiftReg[2];
	            8'd64  :  tx <= ShiftReg[3];
	            8'd80  :  tx <= ShiftReg[4];
	            8'd96  :  tx <= ShiftReg[5];
	            8'd112 :  tx <= ShiftReg[6];
	            8'd128 :  tx <= ShiftReg[7];
	            8'd144 :  tx <= 1'b1;
	        endcase
	    else
	        tx <= 1'b1;
	end
	
	
	
	
	
endmodule    //UARTsend

UART/verilog/UARTsendtest.v
module UARTsendtest();

	reg clk16x;
	reg rst_n;
	reg TransEn;
	reg [7:0] DataToTrans;
	wire BufFull;
	wire tx;

	//---Module instantiation---
	UARTsend UARTsend1(
		.clk16x(clk16x),
		.rst_n(rst_n),
		.TransEn(TransEn),
		.DataToTrans(DataToTrans),
		.BufFull(BufFull),
		.tx(tx));

	//----Code starts here: integrated by Robei-----
	initial begin
	clk16x=0;
	rst_n=1;
	TransEn=0;
	DataToTrans=0;
	#2
	rst_n=0;
	#2
	DataToTrans=8'b10110010;
	#2
	rst_n=1;
	#2
	TransEn=1;
	
	
	#1000
	$finish;
	end
	
	
	always begin
	#1
	clk16x=~clk16x;
	end
	
	
	
	
	initial begin
		$dumpfile ("F:/EDAzhang/eda/UART/UARTsendtest.vcd");
		$dumpvars;
	end
endmodule    //UARTsendtest

UART/UARTsendtest.vcd
$date
	Tue Feb 12 11:12:27 2019
$end
$version
	Icarus Verilog
$end
$timescale
	1s
$end
$scope module UARTsendtest $end
$var wire 1 ! tx $end
$var wire 1 " BufFull $end
$var reg 8 # DataToTrans [7:0] $end
$var reg 1 $ TransEn $end
$var reg 1 % clk16x $end
$var reg 1 & rst_n $end
$scope module UARTsend1 $end
$var wire 8 ' DataToTrans [7:0] $end
$var wire 1 $ TransEn $end
$var wire 1 % clk16x $end
$var wire 1 ( pos_tri $end
$var wire 1 & rst_n $end
$var reg 1 " BufFull $end
$var reg 8 ) ShiftReg [7:0] $end
$var reg 1 * TransEn_r $end
$var reg 8 + cnt [7:0] $end
$var reg 1 , cnt_en $end
$var reg 1 ! tx $end
$upscope $end
$upscope $end
$enddefinitions $end
#0
$dumpvars
x,
bx +
x*
bx )
0(
b0 '
1&
0%
0$
b0 #
x"
x!
$end
#1
0*
b0 +
1!
1%
#2
0"
0,
b0 )
0%
0&
#3
1%
#4
0%
b10110010 #
b10110010 '
#5
1%
#6
0%
1&
#7
1%
#8
b10110010 )
1(
0%
1$
#9
0(
1"
1,
1*
1%
#10
0%
#11
b1 +
0!
1%
#12
0%
#13
b10 +
1%
#14
0%
#15
b11 +
1%
#16
0%
#17
b100 +
1%
#18
0%
#19
b101 +
1%
#20
0%
#21
b110 +
1%
#22
0%
#23
b111 +
1%
#24
0%
#25
b1000 +
1%
#26
0%
#27
b1001 +
1%
#28
0%
#29
b1010 +
1%
#30
0%
#31
b1011 +
1%
#32
0%
#33
b1100 +
1%
#34
0%
#35
b1101 +
1%
#36
0%
#37
b1110 +
1%
#38
0%
#39
b1111 +
1%
#40
0%
#41
b10000 +
1%
#42
0%
#43
b10001 +
1%
#44
0%
#45
b10010 +
1%
#46
0%
#47
b10011 +
1%
#48
0%
#49
b10100 +
1%
#50
0%
#51
b10101 +
1%
#52
0%
#53
b10110 +
1%
#54
0%
#55
b10111 +
1%
#56
0%
#57
b11000 +
1%
#58
0%
#59
b11001 +
1%
#60
0%
#61
b11010 +
1%
#62
0%
#63
b11011 +
1%
#64
0%
#65
b11100 +
1%
#66
0%
#67
b11101 +
1%
#68
0%
#69
b11110 +
1%
#70
0%
#71
b11111 +
1%
#72
0%
#73
b100000 +
1%
#74
0%
#75
b100001 +
1!
1%
#76
0%
#77
b100010 +
1%
#78
0%
#79
b100011 +
1%
#80
0%
#81
b100100 +
1%
#82
0%
#83
b100101 +
1%
#84
0%
#85
b100110 +
1%
#86
0%
#87
b100111 +
1%
#88
0%
#89
b101000 +
1%
#90
0%
#91
b101001 +
1%
#92
0%
#93
b101010 +
1%
#94
0%
#95
b101011 +
1%
#96
0%
#97
b101100 +
1%
#98
0%
#99
b101101 +
1%
#100
0%
#101
b101110 +
1%
#102
0%
#103
b101111 +
1%
#104
0%
#105
b110000 +
1%
#106
0%
#107
b110001 +
0!
1%
#108
0%
#109
b110010 +
1%
#110
0%
#111
b110011 +
1%
#112
0%
#113
b110100 +
1%
#114
0%
#115
b110101 +
1%
#116
0%
#117
b110110 +
1%
#118
0%
#119
b110111 +
1%
#120
0%
#121
b111000 +
1%
#122
0%
#123
b111001 +
1%
#124
0%
#125
b111010 +
1%
#126
0%
#127
b111011 +
1%
#128
0%
#129
b111100 +
1%
#130
0%
#131
b111101 +
1%
#132
0%
#133
b111110 +
1%
#134
0%
#135
b111111 +
1%
#136
0%
#137
b1000000 +
1%
#138
0%
#139
b1000001 +
1%
#140
0%
#141
b1000010 +
1%
#142
0%
#143
b1000011 +
1%
#144
0%
#145
b1000100 +
1%
#146
0%
#147
b1000101 +
1%
#148
0%
#149
b1000110 +
1%
#150
0%
#151
b1000111 +
1%
#152
0%
#153
b1001000 +
1%
#154
0%
#155
b1001001 +
1%
#156
0%
#157
b1001010 +
1%
#158
0%
#159
b1001011 +
1%
#160
0%
#161
b1001100 +
1%
#162
0%
#163
b1001101 +
1%
#164
0%
#165
b1001110 +
1%
#166
0%
#167
b1001111 +
1%
#168
0%
#169
b1010000 +
1%
#170
0%
#171
b1010001 +
1!
1%
#172
0%
#173
b1010010 +
1%
#174
0%
#175
b1010011 +
1%
#176
0%
#177
b1010100 +
1%
#178
0%
#179
b1010101 +
1%
#180
0%
#181
b1010110 +
1%
#182
0%
#183
b1010111 +
1%
#184
0%
#185
b1011000 +
1%
#186
0%
#187
b1011001 +
1%
#188
0%
#189
b1011010 +
1%
#190
0%
#191
b1011011 +
1%
#192
0%
#193
b1011100 +
1%
#194
0%
#195
b1011101 +
1%
#196
0%
#197
b1011110 +
1%
#198
0%
#199
b1011111 +
1%
#200
0%
#201
b1100000 +
1%
#202
0%
#203
b1100001 +
1%
#204
0%
#205
b1100010 +
1%
#206
0%
#207
b1100011 +
1%
#208
0%
#209
b1100100 +
1%
#210
0%
#211
b1100101 +
1%
#212
0%
#213
b1100110 +
1%
#214
0%
#215
b1100111 +
1%
#216
0%
#217
b1101000 +
1%
#218
0%
#219
b1101001 +
1%
#220
0%
#221
b1101010 +
1%
#222
0%
#223
b1101011 +
1%
#224
0%
#225
b1101100 +
1%
#226
0%
#227
b1101101 +
1%
#228
0%
#229
b1101110 +
1%
#230
0%
#231
b1101111 +
1%
#232
0%
#233
b1110000 +
1%
#234
0%
#235
b1110001 +
0!
1%
#236
0%
#237
b1110010 +
1%
#238
0%
#239
b1110011 +
1%
#240
0%
#241
b1110100 +
1%
#242
0%
#243
b1110101 +
1%
#244
0%
#245
b1110110 +
1%
#246
0%
#247
b1110111 +
1%
#248
0%
#249
b1111000 +
1%
#250
0%
#251
b1111001 +
1%
#252
0%
#253
b1111010 +
1%
#254
0%
#255
b1111011 +
1%
#256
0%
#257
b1111100 +
1%
#258
0%
#259
b1111101 +
1%
#260
0%
#261
b1111110 +
1%
#262
0%
#263
b1111111 +
1%
#264
0%
#265
b10000000 +
1%
#266
0%
#267
b10000001 +
1!
1%
#268
0%
#269
b10000010 +
1%
#270
0%
#271
b10000011 +
1%
#272
0%
#273
b10000100 +
1%
#274
0%
#275
b10000101 +
1%
#276
0%
#277
b10000110 +
1%
#278
0%
#279
b10000111 +
1%
#280
0%
#281
b10001000 +
1%
#282
0%
#283
b10001001 +
1%
#284
0%
#285
b10001010 +
1%
#286
0%
#287
b10001011 +
1%
#288
0%
#289
b10001100 +
1%
#290
0%
#291
b10001101 +
1%
#292
0%
#293
b10001110 +
1%
#294
0%
#295
b10001111 +
1%
#296
0%
#297
b10010000 +
1%
#298
0%
#299
b10010001 +
1%
#300
0%
#301
b10010010 +
1%
#302
0%
#303
b10010011 +
1%
#304
0%
#305
b10010100 +
1%
#306
0%
#307
b10010101 +
1%
#308
0%
#309
b10010110 +
1%
#310
0%
#311
b10010111 +
1%
#312
0%
#313
b10011000 +
1%
#314
0%
#315
b10011001 +
1%
#316
0%
#317
b10011010 +
1%
#318
0%
#319
b10011011 +
1%
#320
0%
#321
b10011100 +
1%
#322
0%
#323
b10011101 +
1%
#324
0%
#325
b10011110 +
1%
#326
0%
#327
b10011111 +
1%
#328
0%
#329
b10100000 +
1%
#330
0%
#331
0"
0,
b10100001 +
1%
#332
0%
#333
b0 +
1%
